cx16_conv/__init__.py
cx16_conv/array.py
cx16_conv/cli.py
cx16_conv/image.py
cx16_conv/palette.py
cx16_conv/util.py
cx16_conv-0.1.0.dist-info/entry_points.txt
cx16_conv-0.1.0.dist-info/WHEEL
cx16_conv-0.1.0.dist-info/METADATA
cx16_conv-0.1.0.dist-info/RECORD
