Metadata-Version: 2.1
Name: cx16-conv
Version: 0.1.0
Summary: Conversion utilities for the Commander x16
Home-page: https://github.com/Nitori-/cx16_conv
License: MIT
Keywords: x16,cx16,Commander X16
Author: Jennifer Wilcox
Author-email: jennifer@nitori.org
Requires-Python: >=3.8,<4.0
Classifier: License :: OSI Approved :: MIT License
Classifier: Programming Language :: Python :: 3
Classifier: Programming Language :: Python :: 3.8
Requires-Dist: Pillow (>=7.2.0,<8.0.0)
Requires-Dist: click (>=7.1.2,<8.0.0)
Project-URL: Repository, https://github.com/Nitori-/cx16_conv
